mpscreen/__init__.py
mpscreen/components.py
mpscreen/mpelems.py
mpscreen/mpscreen.py
mpscreen/server.py
mpscreen-0.7.7.dist-info/METADATA
mpscreen-0.7.7.dist-info/WHEEL
mpscreen-0.7.7.dist-info/top_level.txt
mpscreen-0.7.7.dist-info/RECORD
