Metadata-Version: 2.1
Name: mpscreen
Version: 0.7.7
Summary: A Tool for multiprocess screen manipulation
Home-page: UNKNOWN
Author: Jakub Klimek
License: UNKNOWN
Platform: UNKNOWN
Classifier: Programming Language :: Python :: 3
Classifier: License :: OSI Approved :: MIT License
Classifier: Operating System :: POSIX :: Linux
